[
  {
    "id": 1,
    "title": "Basic Life Support",
    "moreInformation": "Pop up box with more BLS info",

    "modules": [
      {
        "id": 1,
        "title": "Learning Objectives",
        "content": [
          "Explain where to find local resus policies and procedures and the current Resuscitation Council UK guidelines",
          "Explain how to carry out an ABCDE approach and recognise the deteriorating patient",
          "Carry out basic airway management",
          "Describe how to confirm cardiac arrest",
          "Describe how to start and maintain effective chest compressions"
        ]
      },
      {
        "id": 2,
        "title": "Session Overview",
        "content": "Test Content 2"
      },
      {
        "id": 3,
        "title": "Introduction",
        "content": "Test Content 3"
      },
      {
        "id": 4,
        "title": "Adult Basic Life Support",
        "content": "Test Content 4"
      },
      {
        "id": 5,
        "title": "Summary",
        "content": "Test Content 5"
      }
    ]
  },
  {
    "id": 2,
    "title": "How To Cook",
    "moreInformation": "Pop up box with more cooking info",

    "modules": [
      {
        "id": 1,
        "title": "Learning Objectives",
        "content": [
          "Learn to choose ingredients",
          "Learn to use the ingredients"
        ]
      },
      {
        "id": 2,
        "title": "Session Overview",
        "content": "Cooking test content 1"
      },
      {
        "id": 3,
        "title": "What do you need",
        "content": "Cooking test content 2"
      },
      {
        "id": 4,
        "title": "Let's cook",
        "content": "Cooking test content 3 "
      },
      {
        "id": 5,
        "title": "Let us eat",
        "content": "Cooking test content 4"
      }
    ]
  },
  {
    "id": 3,
    "title": "How To Cook",

    "modules": [
      {
        "id": 1,
        "title": "Learning Objectives",
        "content": [
          "Learn to choose ingredients",
          "Learn to use the ingredients"
        ]
      },
      {
        "id": 2,
        "title": "Session Overview",
        "content": "Cooking test content 1"
      },
      {
        "id": 3,
        "title": "What do you need",
        "content": "Cooking test content 2"
      },
      {
        "id": 4,
        "title": "Let's cook",
        "content": "Cooking test content 3 "
      },
      {
        "id": 5,
        "title": "Let us eat",
        "content": "Cooking test content 4"
      }
    ]
  }
]
